awareness/__init__.py
awareness/algorithm.py
awareness/backend.py
awareness/component.py
awareness/data.py
awareness/exception.py
awareness/factory.py
awareness/misc.py
awareness/operator.py
awareness/protocol.py
awareness-25.3.2.dist-info/DESCRIPTION.rst
awareness-25.3.2.dist-info/METADATA
awareness-25.3.2.dist-info/RECORD
awareness-25.3.2.dist-info/WHEEL
awareness-25.3.2.dist-info/metadata.json
awareness-25.3.2.dist-info/top_level.txt
