Metadata-Version: 2.0
Name: awareness
Version: 25.3.2
Summary: The new architecture of co-computation for data processing and machine learning.
Home-page: https://github.com/awrns/awareness
Author: Aedan Cullen
Author-email: aedancullen@gmail.com
License: UNKNOWN
Keywords: networking,ai,machine,learning,software,architecture,library,python,module,cocomputation,protocol,cloud,computing,iot
Platform: UNKNOWN
Requires-Dist: Theano (==0.9.0)
